{
    "type":  "vsq:enchanting",
    "category":  "armor",
    "group":  "feather_falling",
    "level":  4,
    "consumed_levels":  4,
    "name":  {
                 "text":  "Feather Falling IV"
             },
    "description":  {
                        "text":  "Feather Falling IV"
                    },
    "input":  {
                  "tag":  "minecraft:enchantable/foot_armor",
                  "count":  1
              },
    "material":  {
                     "item":  "minecraft:lapis_lazuli",
                     "count":  1
                 },
    "ingredients":  [
                        {
                            "item":  "minecraft:book",
                            "count":  1
                        },
                        {
                            "item":  "minecraft:book",
                            "count":  1
                        },
                        {
                            "item":  "minecraft:book",
                            "count":  1
                        },
                        {
                            "item":  "minecraft:book",
                            "count":  1
                        }
                    ],
    "component_modifier":  {
                               "minecraft:enchantments":  {
                                                              "minecraft:feather_falling":  4
                                                          }
                           }
}
